{
  "heroes": [
    {
      "name": "MissKetty",
      "strength": 7,
      "intelligence": 8,
      "speed": 7,
      "id": 12
    },
    {
      "name": "Robot",
      "strength": "1",
      "intelligence": "3",
      "speed": "6",
      "id": 13
    },
    {
      "name": "Barbie",
      "strength": "2",
      "intelligence": "2",
      "speed": "3",
      "id": 14
    },
    {
      "name": "Superman",
      "strength": "3",
      "intelligence": "3",
      "speed": "3",
      "id": 15
    },
    {
      "name": "SuperGirl",
      "strength": "4",
      "intelligence": "4",
      "speed": "2",
      "id": 16
    },
    {
      "name": "Lux",
      "strength": "1",
      "intelligence": "1",
      "speed": "1",
      "id": 17
    }
  ],
  "squads": [
    [],
    [],
    [
      [
        {
          "name": "SuperGirl",
          "strength": "4",
          "intelligence": "4",
          "speed": "2",
          "id": 16
        }
      ],
      [
        {
          "name": "Superman",
          "strength": "3",
          "intelligence": "3",
          "speed": "3",
          "id": 15
        }
      ]
    ],
    [
      [
        {
          "name": "SuperGirl",
          "strength": "4",
          "intelligence": "4",
          "speed": "2",
          "id": 16
        }
      ],
      [
        {
          "name": "Superman",
          "strength": "3",
          "intelligence": "3",
          "speed": "3",
          "id": 15
        }
      ],
      [
        {
          "name": "SuperGirl",
          "strength": "4",
          "intelligence": "4",
          "speed": "2",
          "id": 16
        }
      ],
      [
        {
          "name": "Superman",
          "strength": "3",
          "intelligence": "3",
          "speed": "3",
          "id": 15
        }
      ]
    ],
    [
      [
        {
          "name": "SuperGirl",
          "strength": "4",
          "intelligence": "4",
          "speed": "2",
          "id": 16
        }
      ]
    ],
    [
      [
        {
          "name": "SuperGirl",
          "strength": "4",
          "intelligence": "4",
          "speed": "2",
          "id": 16
        }
      ],
      [
        {
          "name": "Superman",
          "strength": "3",
          "intelligence": "3",
          "speed": "3",
          "id": 15
        }
      ]
    ],
    [
      [
        {
          "name": "SuperGirl",
          "strength": "4",
          "intelligence": "4",
          "speed": "2",
          "id": 16
        }
      ],
      [
        {
          "name": "Superman",
          "strength": "3",
          "intelligence": "3",
          "speed": "3",
          "id": 15
        }
      ]
    ],
    [
      [
        {
          "name": "SuperGirl",
          "strength": "4",
          "intelligence": "4",
          "speed": "2",
          "id": 16
        }
      ],
      [
        {
          "name": "Superman",
          "strength": "3",
          "intelligence": "3",
          "speed": "3",
          "id": 15
        }
      ]
    ],
    [
      [
        {
          "name": "SuperGirl",
          "strength": "4",
          "intelligence": "4",
          "speed": "2",
          "id": 16
        }
      ],
      [
        {
          "name": "Barbie",
          "strength": "2",
          "intelligence": "2",
          "speed": "3",
          "id": 14
        }
      ]
    ],
    [
      [
        {
          "name": "SuperGirl",
          "strength": "4",
          "intelligence": "4",
          "speed": "2",
          "id": 16
        }
      ],
      [
        {
          "name": "Superman",
          "strength": "3",
          "intelligence": "3",
          "speed": "3",
          "id": 15
        }
      ]
    ],
    [
      [
        {
          "name": "SuperGirl",
          "strength": "4",
          "intelligence": "4",
          "speed": "2",
          "id": 16
        }
      ],
      [
        {
          "name": "Superman",
          "strength": "3",
          "intelligence": "3",
          "speed": "3",
          "id": 15
        }
      ]
    ],
    [
      [
        {
          "name": "SuperGirl",
          "strength": "4",
          "intelligence": "4",
          "speed": "2",
          "id": 16
        }
      ]
    ],
    [
      [
        {
          "name": "SuperGirl",
          "strength": "4",
          "intelligence": "4",
          "speed": "2",
          "id": 16
        }
      ],
      [
        {
          "name": "Superman",
          "strength": "3",
          "intelligence": "3",
          "speed": "3",
          "id": 15
        }
      ]
    ],
    [
      [
        {
          "name": "SuperGirl",
          "strength": "4",
          "intelligence": "4",
          "speed": "2",
          "id": 16
        }
      ],
      [
        {
          "name": "Superman",
          "strength": "3",
          "intelligence": "3",
          "speed": "3",
          "id": 15
        }
      ]
    ],
    [
      [
        {
          "name": "SuperGirl",
          "strength": "4",
          "intelligence": "4",
          "speed": "2",
          "id": 16
        }
      ],
      [
        {
          "name": "Superman",
          "strength": "3",
          "intelligence": "3",
          "speed": "3",
          "id": 15
        }
      ]
    ],
    [
      [
        {
          "name": "SuperGirl",
          "strength": "4",
          "intelligence": "4",
          "speed": "2",
          "id": 16
        }
      ],
      [
        {
          "name": "Superman",
          "strength": "3",
          "intelligence": "3",
          "speed": "3",
          "id": 15
        }
      ]
    ],
    [
      [
        {
          "name": "SuperGirl",
          "strength": "4",
          "intelligence": "4",
          "speed": "2",
          "id": 16
        }
      ],
      [
        {
          "name": "Superman",
          "strength": "3",
          "intelligence": "3",
          "speed": "3",
          "id": 15
        }
      ],
      [
        {
          "name": "Barbie",
          "strength": "2",
          "intelligence": "2",
          "speed": "3",
          "id": 14
        }
      ],
      [
        {
          "name": "Robot",
          "strength": "1",
          "intelligence": "3",
          "speed": "6",
          "id": 13
        }
      ]
    ],
    [
      [
        {
          "name": "SuperGirl",
          "strength": "4",
          "intelligence": "4",
          "speed": "2",
          "id": 16
        }
      ],
      [
        {
          "name": "Superman",
          "strength": "3",
          "intelligence": "3",
          "speed": "3",
          "id": 15
        }
      ]
    ],
    [
      [
        {
          "name": "SuperGirl",
          "strength": "4",
          "intelligence": "4",
          "speed": "2",
          "id": 16
        }
      ]
    ],
    [
      [
        {
          "name": "SuperGirl",
          "strength": "4",
          "intelligence": "4",
          "speed": "2",
          "id": 16
        }
      ]
    ],
    [
      [
        {
          "name": "SuperGirl",
          "strength": "4",
          "intelligence": "4",
          "speed": "2",
          "id": 16
        }
      ]
    ],
    [
      [
        {
          "name": "SuperGirl",
          "strength": "4",
          "intelligence": "4",
          "speed": "2",
          "id": 16
        }
      ],
      [
        {
          "name": "Superman",
          "strength": "3",
          "intelligence": "3",
          "speed": "3",
          "id": 15
        }
      ]
    ],
    [
      [
        {
          "name": "SuperGirl",
          "strength": "4",
          "intelligence": "4",
          "speed": "2",
          "id": 16
        }
      ]
    ],
    [
      [
        {
          "name": "SuperGirl",
          "strength": "4",
          "intelligence": "4",
          "speed": "2",
          "id": 16
        }
      ],
      [
        {
          "name": "Superman",
          "strength": "3",
          "intelligence": "3",
          "speed": "3",
          "id": 15
        }
      ]
    ],
    [
      [
        {
          "name": "SuperGirl",
          "strength": "4",
          "intelligence": "4",
          "speed": "2",
          "id": 16
        }
      ],
      [
        {
          "name": "Superman",
          "strength": "3",
          "intelligence": "3",
          "speed": "3",
          "id": 15
        }
      ],
      [
        {
          "name": "SuperGirl",
          "strength": "4",
          "intelligence": "4",
          "speed": "2",
          "id": 16
        }
      ]
    ],
    [
      [
        {
          "name": "SuperGirl",
          "strength": "4",
          "intelligence": "4",
          "speed": "2",
          "id": 16
        }
      ]
    ],
    [
      [
        {
          "name": "SuperGirl",
          "strength": "4",
          "intelligence": "4",
          "speed": "2",
          "id": 16
        }
      ],
      [
        {
          "name": "Superman",
          "strength": "3",
          "intelligence": "3",
          "speed": "3",
          "id": 15
        }
      ]
    ],
    [
      [
        {
          "name": "SuperGirl",
          "strength": "4",
          "intelligence": "4",
          "speed": "2",
          "id": 16
        }
      ],
      [
        {
          "name": "Superman",
          "strength": "3",
          "intelligence": "3",
          "speed": "3",
          "id": 15
        }
      ],
      [
        {
          "name": "SuperGirl",
          "strength": "4",
          "intelligence": "4",
          "speed": "2",
          "id": 16
        }
      ]
    ],
    [
      [
        {
          "name": "SuperGirl",
          "strength": "4",
          "intelligence": "4",
          "speed": "2",
          "id": 16
        }
      ],
      [
        {
          "name": "Superman",
          "strength": "3",
          "intelligence": "3",
          "speed": "3",
          "id": 15
        }
      ],
      [
        {
          "name": "SuperGirl",
          "strength": "4",
          "intelligence": "4",
          "speed": "2",
          "id": 16
        }
      ],
      [
        {
          "name": "Superman",
          "strength": "3",
          "intelligence": "3",
          "speed": "3",
          "id": 15
        }
      ],
      [
        {
          "name": "SuperGirl",
          "strength": "4",
          "intelligence": "4",
          "speed": "2",
          "id": 16
        }
      ]
    ],
    [
      [
        {
          "name": "SuperGirl",
          "strength": "4",
          "intelligence": "4",
          "speed": "2",
          "id": 16
        }
      ]
    ],
    [
      [
        {
          "name": "SuperGirl",
          "strength": "4",
          "intelligence": "4",
          "speed": "2",
          "id": 16
        }
      ],
      [
        {
          "name": "Superman",
          "strength": "3",
          "intelligence": "3",
          "speed": "3",
          "id": 15
        }
      ],
      [
        {
          "name": "SuperGirl",
          "strength": "4",
          "intelligence": "4",
          "speed": "2",
          "id": 16
        }
      ]
    ],
    [
      [
        {
          "name": "SuperGirl",
          "strength": "4",
          "intelligence": "4",
          "speed": "2",
          "id": 16
        }
      ],
      [
        {
          "name": "Superman",
          "strength": "3",
          "intelligence": "3",
          "speed": "3",
          "id": 15
        }
      ]
    ],
    [
      [
        {
          "name": "SuperGirl",
          "strength": "4",
          "intelligence": "4",
          "speed": "2",
          "id": 16
        }
      ]
    ],
    [
      [
        {
          "name": "SuperGirl",
          "strength": "4",
          "intelligence": "4",
          "speed": "2",
          "id": 16
        }
      ]
    ],
    [
      [
        {
          "name": "SuperGirl",
          "strength": "4",
          "intelligence": "4",
          "speed": "2",
          "id": 16
        }
      ],
      [
        {
          "name": "Superman",
          "strength": "3",
          "intelligence": "3",
          "speed": "3",
          "id": 15
        }
      ],
      [
        {
          "name": "Barbie",
          "strength": "2",
          "intelligence": "2",
          "speed": "3",
          "id": 14
        }
      ]
    ],
    [
      [
        {
          "name": "SuperGirl",
          "strength": "4",
          "intelligence": "4",
          "speed": "2",
          "id": 16
        }
      ],
      [
        {
          "name": "Superman",
          "strength": "3",
          "intelligence": "3",
          "speed": "3",
          "id": 15
        }
      ],
      [
        {
          "name": "Barbie",
          "strength": "2",
          "intelligence": "2",
          "speed": "3",
          "id": 14
        }
      ],
      [
        {
          "name": "SuperGirl",
          "strength": "4",
          "intelligence": "4",
          "speed": "2",
          "id": 16
        }
      ],
      [
        {
          "name": "Robot",
          "strength": "1",
          "intelligence": "3",
          "speed": "6",
          "id": 13
        }
      ],
      [
        {
          "name": "MissKetty",
          "strength": 7,
          "intelligence": 8,
          "speed": 7,
          "id": 12
        }
      ]
    ],
    [
      [
        {
          "name": "SuperGirl",
          "strength": "4",
          "intelligence": "4",
          "speed": "2",
          "id": 16
        }
      ]
    ],
    [
      [
        {
          "name": "SuperGirl",
          "strength": "4",
          "intelligence": "4",
          "speed": "2",
          "id": 16
        }
      ],
      [
        {
          "name": "Superman",
          "strength": "3",
          "intelligence": "3",
          "speed": "3",
          "id": 15
        }
      ]
    ],
    [
      [
        {
          "name": "SuperGirl",
          "strength": "4",
          "intelligence": "4",
          "speed": "2",
          "id": 16
        }
      ]
    ],
    [
      [
        {
          "name": "SuperGirl",
          "strength": "4",
          "intelligence": "4",
          "speed": "2",
          "id": 16
        }
      ],
      [
        {
          "name": "Superman",
          "strength": "3",
          "intelligence": "3",
          "speed": "3",
          "id": 15
        }
      ],
      [
        {
          "name": "Barbie",
          "strength": "2",
          "intelligence": "2",
          "speed": "3",
          "id": 14
        }
      ]
    ],
    [
      [
        {
          "name": "SuperGirl",
          "strength": "4",
          "intelligence": "4",
          "speed": "2",
          "id": 16
        }
      ],
      [
        {
          "name": "Superman",
          "strength": "3",
          "intelligence": "3",
          "speed": "3",
          "id": 15
        }
      ],
      [
        {
          "name": "Barbie",
          "strength": "2",
          "intelligence": "2",
          "speed": "3",
          "id": 14
        }
      ],
      [
        {
          "name": "SuperGirl",
          "strength": "4",
          "intelligence": "4",
          "speed": "2",
          "id": 16
        }
      ],
      [
        {
          "name": "Robot",
          "strength": "1",
          "intelligence": "3",
          "speed": "6",
          "id": 13
        }
      ],
      [
        {
          "name": "MissKetty",
          "strength": 7,
          "intelligence": 8,
          "speed": 7,
          "id": 12
        }
      ]
    ],
    [
      [
        {
          "name": "SuperGirl",
          "strength": "4",
          "intelligence": "4",
          "speed": "2",
          "id": 16
        }
      ],
      [
        {
          "name": "Superman",
          "strength": "3",
          "intelligence": "3",
          "speed": "3",
          "id": 15
        }
      ],
      [
        {
          "name": "Barbie",
          "strength": "2",
          "intelligence": "2",
          "speed": "3",
          "id": 14
        }
      ],
      [
        {
          "name": "SuperGirl",
          "strength": "4",
          "intelligence": "4",
          "speed": "2",
          "id": 16
        }
      ],
      [
        {
          "name": "Robot",
          "strength": "1",
          "intelligence": "3",
          "speed": "6",
          "id": 13
        }
      ],
      [
        {
          "name": "MissKetty",
          "strength": 7,
          "intelligence": 8,
          "speed": 7,
          "id": 12
        }
      ],
      [
        {
          "name": "Superman",
          "strength": "3",
          "intelligence": "3",
          "speed": "3",
          "id": 15
        }
      ],
      [
        {
          "name": "MissKetty",
          "strength": 7,
          "intelligence": 8,
          "speed": 7,
          "id": 12
        }
      ]
    ],
    [
      [
        {
          "name": "SuperGirl",
          "strength": "4",
          "intelligence": "4",
          "speed": "2",
          "id": 16
        }
      ],
      [
        {
          "name": "Superman",
          "strength": "3",
          "intelligence": "3",
          "speed": "3",
          "id": 15
        }
      ]
    ],
    [
      [
        {
          "name": "SuperGirl",
          "strength": "4",
          "intelligence": "4",
          "speed": "2",
          "id": 16
        }
      ],
      [
        {
          "name": "Superman",
          "strength": "3",
          "intelligence": "3",
          "speed": "3",
          "id": 15
        }
      ],
      [
        {
          "name": "Barbie",
          "strength": "2",
          "intelligence": "2",
          "speed": "3",
          "id": 14
        }
      ],
      [
        {
          "name": "Robot",
          "strength": "1",
          "intelligence": "3",
          "speed": "6",
          "id": 13
        }
      ]
    ],
    [
      [
        {
          "name": "SuperGirl",
          "strength": "4",
          "intelligence": "4",
          "speed": "2",
          "id": 16
        }
      ],
      [
        {
          "name": "Superman",
          "strength": "3",
          "intelligence": "3",
          "speed": "3",
          "id": 15
        }
      ]
    ],
    [
      [
        {
          "name": "SuperGirl",
          "strength": "4",
          "intelligence": "4",
          "speed": "2",
          "id": 16
        }
      ],
      [
        {
          "name": "Superman",
          "strength": "3",
          "intelligence": "3",
          "speed": "3",
          "id": 15
        }
      ],
      [
        {
          "name": "Barbie",
          "strength": "2",
          "intelligence": "2",
          "speed": "3",
          "id": 14
        }
      ],
      [
        {
          "name": "Robot",
          "strength": "1",
          "intelligence": "3",
          "speed": "6",
          "id": 13
        }
      ]
    ],
    [
      [
        {
          "name": "SuperGirl",
          "strength": "4",
          "intelligence": "4",
          "speed": "2",
          "id": 16
        }
      ],
      [
        {
          "name": "Superman",
          "strength": "3",
          "intelligence": "3",
          "speed": "3",
          "id": 15
        }
      ],
      [
        {
          "name": "Barbie",
          "strength": "2",
          "intelligence": "2",
          "speed": "3",
          "id": 14
        }
      ],
      [
        {
          "name": "Robot",
          "strength": "1",
          "intelligence": "3",
          "speed": "6",
          "id": 13
        }
      ],
      [
        {
          "name": "SuperGirl",
          "strength": "4",
          "intelligence": "4",
          "speed": "2",
          "id": 16
        }
      ],
      [
        {
          "name": "Robot",
          "strength": "1",
          "intelligence": "3",
          "speed": "6",
          "id": 13
        }
      ]
    ],
    [
      [
        {
          "name": "SuperGirl",
          "strength": "4",
          "intelligence": "4",
          "speed": "2",
          "id": 16
        }
      ],
      [
        {
          "name": "Superman",
          "strength": "3",
          "intelligence": "3",
          "speed": "3",
          "id": 15
        }
      ]
    ],
    [
      [
        {
          "name": "SuperGirl",
          "strength": "4",
          "intelligence": "4",
          "speed": "2",
          "id": 16
        }
      ],
      [
        {
          "name": "Superman",
          "strength": "3",
          "intelligence": "3",
          "speed": "3",
          "id": 15
        }
      ],
      [
        {
          "name": "Barbie",
          "strength": "2",
          "intelligence": "2",
          "speed": "3",
          "id": 14
        }
      ],
      [
        {
          "name": "Robot",
          "strength": "1",
          "intelligence": "3",
          "speed": "6",
          "id": 13
        }
      ]
    ],
    [
      [
        {
          "name": "SuperGirl",
          "strength": "4",
          "intelligence": "4",
          "speed": "2",
          "id": 16
        }
      ],
      [
        {
          "name": "Superman",
          "strength": "3",
          "intelligence": "3",
          "speed": "3",
          "id": 15
        }
      ],
      [
        {
          "name": "Barbie",
          "strength": "2",
          "intelligence": "2",
          "speed": "3",
          "id": 14
        }
      ],
      [
        {
          "name": "Robot",
          "strength": "1",
          "intelligence": "3",
          "speed": "6",
          "id": 13
        }
      ],
      [
        {
          "name": "SuperGirl",
          "strength": "4",
          "intelligence": "4",
          "speed": "2",
          "id": 16
        }
      ]
    ],
    [
      [
        {
          "name": "SuperGirl",
          "strength": "4",
          "intelligence": "4",
          "speed": "2",
          "id": 16
        }
      ]
    ],
    [
      [
        {
          "name": "SuperGirl",
          "strength": "4",
          "intelligence": "4",
          "speed": "2",
          "id": 16
        }
      ]
    ],
    [
      [
        {
          "name": "SuperGirl",
          "strength": "4",
          "intelligence": "4",
          "speed": "2",
          "id": 16
        }
      ],
      [
        {
          "name": "Superman",
          "strength": "3",
          "intelligence": "3",
          "speed": "3",
          "id": 15
        }
      ]
    ],
    [
      [
        {
          "name": "SuperGirl",
          "strength": "4",
          "intelligence": "4",
          "speed": "2",
          "id": 16
        }
      ],
      [
        {
          "name": "Superman",
          "strength": "3",
          "intelligence": "3",
          "speed": "3",
          "id": 15
        }
      ]
    ],
    [
      [
        {
          "name": "SuperGirl",
          "strength": "4",
          "intelligence": "4",
          "speed": "2",
          "id": 16
        }
      ],
      [
        {
          "name": "Superman",
          "strength": "3",
          "intelligence": "3",
          "speed": "3",
          "id": 15
        }
      ]
    ],
    [
      [
        {
          "name": "SuperGirl",
          "strength": "4",
          "intelligence": "4",
          "speed": "2",
          "id": 16
        }
      ],
      [
        {
          "name": "Superman",
          "strength": "3",
          "intelligence": "3",
          "speed": "3",
          "id": 15
        }
      ]
    ],
    [
      [
        {
          "name": "SuperGirl",
          "strength": "4",
          "intelligence": "4",
          "speed": "2",
          "id": 16
        }
      ],
      [
        {
          "name": "Superman",
          "strength": "3",
          "intelligence": "3",
          "speed": "3",
          "id": 15
        }
      ],
      [
        {
          "name": "SuperGirl",
          "strength": "4",
          "intelligence": "4",
          "speed": "2",
          "id": 16
        }
      ],
      [
        {
          "name": "Superman",
          "strength": "3",
          "intelligence": "3",
          "speed": "3",
          "id": 15
        }
      ],
      [
        {
          "name": "SuperGirl",
          "strength": "4",
          "intelligence": "4",
          "speed": "2",
          "id": 16
        }
      ],
      [
        {
          "name": "Superman",
          "strength": "3",
          "intelligence": "3",
          "speed": "3",
          "id": 15
        }
      ]
    ],
    [
      [
        {
          "name": "SuperGirl",
          "strength": "4",
          "intelligence": "4",
          "speed": "2",
          "id": 16
        }
      ],
      [
        {
          "name": "Superman",
          "strength": "3",
          "intelligence": "3",
          "speed": "3",
          "id": 15
        }
      ]
    ],
    [
      [
        {
          "name": "SuperGirl",
          "strength": "4",
          "intelligence": "4",
          "speed": "2",
          "id": 16
        }
      ],
      [
        {
          "name": "Superman",
          "strength": "3",
          "intelligence": "3",
          "speed": "3",
          "id": 15
        }
      ],
      [
        {
          "name": "Barbie",
          "strength": "2",
          "intelligence": "2",
          "speed": "3",
          "id": 14
        }
      ],
      [
        {
          "name": "Robot",
          "strength": "1",
          "intelligence": "3",
          "speed": "6",
          "id": 13
        }
      ]
    ],
    [
      [
        {
          "name": "SuperGirl",
          "strength": "4",
          "intelligence": "4",
          "speed": "2",
          "id": 16
        }
      ],
      [
        {
          "name": "Superman",
          "strength": "3",
          "intelligence": "3",
          "speed": "3",
          "id": 15
        }
      ],
      [
        {
          "name": "Barbie",
          "strength": "2",
          "intelligence": "2",
          "speed": "3",
          "id": 14
        }
      ],
      [
        {
          "name": "Robot",
          "strength": "1",
          "intelligence": "3",
          "speed": "6",
          "id": 13
        }
      ],
      [
        {
          "name": "SuperGirl",
          "strength": "4",
          "intelligence": "4",
          "speed": "2",
          "id": 16
        }
      ],
      [
        {
          "name": "Robot",
          "strength": "1",
          "intelligence": "3",
          "speed": "6",
          "id": 13
        }
      ]
    ],
    [
      [
        {
          "name": "SuperGirl",
          "strength": "4",
          "intelligence": "4",
          "speed": "2",
          "id": 16
        }
      ],
      [
        {
          "name": "Superman",
          "strength": "3",
          "intelligence": "3",
          "speed": "3",
          "id": 15
        }
      ],
      [
        {
          "name": "Barbie",
          "strength": "2",
          "intelligence": "2",
          "speed": "3",
          "id": 14
        }
      ],
      [
        {
          "name": "Robot",
          "strength": "1",
          "intelligence": "3",
          "speed": "6",
          "id": 13
        }
      ],
      [
        {
          "name": "SuperGirl",
          "strength": "4",
          "intelligence": "4",
          "speed": "2",
          "id": 16
        }
      ],
      [
        {
          "name": "Robot",
          "strength": "1",
          "intelligence": "3",
          "speed": "6",
          "id": 13
        }
      ],
      [
        {
          "name": "Superman",
          "strength": "3",
          "intelligence": "3",
          "speed": "3",
          "id": 15
        }
      ],
      [
        {
          "name": "Robot",
          "strength": "1",
          "intelligence": "3",
          "speed": "6",
          "id": 13
        }
      ]
    ],
    [
      [
        {
          "name": "SuperGirl",
          "strength": "4",
          "intelligence": "4",
          "speed": "2",
          "id": 16
        }
      ]
    ],
    [
      [
        {
          "name": "SuperGirl",
          "strength": "4",
          "intelligence": "4",
          "speed": "2",
          "id": 16
        }
      ],
      [
        {
          "name": "Superman",
          "strength": "3",
          "intelligence": "3",
          "speed": "3",
          "id": 15
        }
      ],
      [
        {
          "name": "Barbie",
          "strength": "2",
          "intelligence": "2",
          "speed": "3",
          "id": 14
        }
      ]
    ],
    [
      [
        {
          "name": "SuperGirl",
          "strength": "4",
          "intelligence": "4",
          "speed": "2",
          "id": 16
        }
      ],
      [
        {
          "name": "SuperGirl",
          "strength": "4",
          "intelligence": "4",
          "speed": "2",
          "id": 16
        }
      ],
      [
        {
          "name": "Superman",
          "strength": "3",
          "intelligence": "3",
          "speed": "3",
          "id": 15
        }
      ],
      [
        {
          "name": "SuperGirl",
          "strength": "4",
          "intelligence": "4",
          "speed": "2",
          "id": 16
        }
      ],
      [
        {
          "name": "Superman",
          "strength": "3",
          "intelligence": "3",
          "speed": "3",
          "id": 15
        }
      ]
    ],
    [
      [
        {
          "name": "SuperGirl",
          "strength": "4",
          "intelligence": "4",
          "speed": "2",
          "id": 16
        }
      ],
      [
        {
          "name": "SuperGirl",
          "strength": "4",
          "intelligence": "4",
          "speed": "2",
          "id": 16
        }
      ],
      [
        {
          "name": "Superman",
          "strength": "3",
          "intelligence": "3",
          "speed": "3",
          "id": 15
        }
      ],
      [
        {
          "name": "SuperGirl",
          "strength": "4",
          "intelligence": "4",
          "speed": "2",
          "id": 16
        }
      ]
    ],
    [
      [
        {
          "name": "SuperGirl",
          "strength": "4",
          "intelligence": "4",
          "speed": "2",
          "id": 16
        }
      ],
      [
        {
          "name": "SuperGirl",
          "strength": "4",
          "intelligence": "4",
          "speed": "2",
          "id": 16
        }
      ],
      [
        {
          "name": "Superman",
          "strength": "3",
          "intelligence": "3",
          "speed": "3",
          "id": 15
        }
      ],
      [
        {
          "name": "SuperGirl",
          "strength": "4",
          "intelligence": "4",
          "speed": "2",
          "id": 16
        }
      ],
      [
        {
          "name": "Superman",
          "strength": "3",
          "intelligence": "3",
          "speed": "3",
          "id": 15
        }
      ]
    ],
    [
      [
        {
          "name": "SuperGirl",
          "strength": "4",
          "intelligence": "4",
          "speed": "2",
          "id": 16
        }
      ],
      [
        {
          "name": "SuperGirl",
          "strength": "4",
          "intelligence": "4",
          "speed": "2",
          "id": 16
        }
      ],
      [
        {
          "name": "Superman",
          "strength": "3",
          "intelligence": "3",
          "speed": "3",
          "id": 15
        }
      ],
      [
        {
          "name": "SuperGirl",
          "strength": "4",
          "intelligence": "4",
          "speed": "2",
          "id": 16
        }
      ],
      [
        {
          "name": "Superman",
          "strength": "3",
          "intelligence": "3",
          "speed": "3",
          "id": 15
        }
      ],
      [
        {
          "name": "SuperGirl",
          "strength": "4",
          "intelligence": "4",
          "speed": "2",
          "id": 16
        }
      ],
      [
        {
          "name": "Superman",
          "strength": "3",
          "intelligence": "3",
          "speed": "3",
          "id": 15
        }
      ]
    ],
    [
      [
        {
          "name": "SuperGirl",
          "strength": "4",
          "intelligence": "4",
          "speed": "2",
          "id": 16
        }
      ],
      [
        {
          "name": "SuperGirl",
          "strength": "4",
          "intelligence": "4",
          "speed": "2",
          "id": 16
        }
      ],
      [
        {
          "name": "Superman",
          "strength": "3",
          "intelligence": "3",
          "speed": "3",
          "id": 15
        }
      ],
      [
        {
          "name": "SuperGirl",
          "strength": "4",
          "intelligence": "4",
          "speed": "2",
          "id": 16
        }
      ],
      [
        {
          "name": "Superman",
          "strength": "3",
          "intelligence": "3",
          "speed": "3",
          "id": 15
        }
      ],
      [
        {
          "name": "SuperGirl",
          "strength": "4",
          "intelligence": "4",
          "speed": "2",
          "id": 16
        }
      ],
      [
        {
          "name": "Superman",
          "strength": "3",
          "intelligence": "3",
          "speed": "3",
          "id": 15
        }
      ],
      [
        {
          "name": "Barbie",
          "strength": "2",
          "intelligence": "2",
          "speed": "3",
          "id": 14
        }
      ],
      [
        {
          "name": "Superman",
          "strength": "3",
          "intelligence": "3",
          "speed": "3",
          "id": 15
        }
      ]
    ],
    [
      [
        {
          "name": "SuperGirl",
          "strength": "4",
          "intelligence": "4",
          "speed": "2",
          "id": 16
        }
      ],
      [
        {
          "name": "SuperGirl",
          "strength": "4",
          "intelligence": "4",
          "speed": "2",
          "id": 16
        }
      ],
      [
        {
          "name": "Superman",
          "strength": "3",
          "intelligence": "3",
          "speed": "3",
          "id": 15
        }
      ],
      [
        {
          "name": "SuperGirl",
          "strength": "4",
          "intelligence": "4",
          "speed": "2",
          "id": 16
        }
      ],
      [
        {
          "name": "Superman",
          "strength": "3",
          "intelligence": "3",
          "speed": "3",
          "id": 15
        }
      ],
      [
        {
          "name": "SuperGirl",
          "strength": "4",
          "intelligence": "4",
          "speed": "2",
          "id": 16
        }
      ],
      [
        {
          "name": "Superman",
          "strength": "3",
          "intelligence": "3",
          "speed": "3",
          "id": 15
        }
      ],
      [
        {
          "name": "Barbie",
          "strength": "2",
          "intelligence": "2",
          "speed": "3",
          "id": 14
        }
      ],
      [
        {
          "name": "Superman",
          "strength": "3",
          "intelligence": "3",
          "speed": "3",
          "id": 15
        }
      ],
      [
        {
          "name": "SuperGirl",
          "strength": "4",
          "intelligence": "4",
          "speed": "2",
          "id": 16
        }
      ],
      [
        {
          "name": "Barbie",
          "strength": "2",
          "intelligence": "2",
          "speed": "3",
          "id": 14
        }
      ]
    ],
    [
      [
        {
          "name": "SuperGirl",
          "strength": "4",
          "intelligence": "4",
          "speed": "2",
          "id": 16
        }
      ],
      [
        {
          "name": "SuperGirl",
          "strength": "4",
          "intelligence": "4",
          "speed": "2",
          "id": 16
        }
      ],
      [
        {
          "name": "Superman",
          "strength": "3",
          "intelligence": "3",
          "speed": "3",
          "id": 15
        }
      ]
    ],
    [
      [
        {
          "name": "SuperGirl",
          "strength": "4",
          "intelligence": "4",
          "speed": "2",
          "id": 16
        }
      ],
      [
        {
          "name": "SuperGirl",
          "strength": "4",
          "intelligence": "4",
          "speed": "2",
          "id": 16
        }
      ],
      [
        {
          "name": "Superman",
          "strength": "3",
          "intelligence": "3",
          "speed": "3",
          "id": 15
        }
      ],
      [
        {
          "name": "Barbie",
          "strength": "2",
          "intelligence": "2",
          "speed": "3",
          "id": 14
        }
      ],
      [
        {
          "name": "Robot",
          "strength": "1",
          "intelligence": "3",
          "speed": "6",
          "id": 13
        }
      ]
    ],
    [
      [
        {
          "name": "SuperGirl",
          "strength": "4",
          "intelligence": "4",
          "speed": "2",
          "id": 16
        }
      ],
      [
        {
          "name": "Superman",
          "strength": "3",
          "intelligence": "3",
          "speed": "3",
          "id": 15
        }
      ]
    ],
    [
      [
        {
          "name": "SuperGirl",
          "strength": "4",
          "intelligence": "4",
          "speed": "2",
          "id": 16
        }
      ],
      [
        {
          "name": "Superman",
          "strength": "3",
          "intelligence": "3",
          "speed": "3",
          "id": 15
        }
      ],
      [
        {
          "name": "Barbie",
          "strength": "2",
          "intelligence": "2",
          "speed": "3",
          "id": 14
        }
      ]
    ],
    [
      [
        {
          "name": "SuperGirl",
          "strength": "4",
          "intelligence": "4",
          "speed": "2",
          "id": 16
        }
      ],
      [
        {
          "name": "Superman",
          "strength": "3",
          "intelligence": "3",
          "speed": "3",
          "id": 15
        }
      ],
      [
        {
          "name": "Barbie",
          "strength": "2",
          "intelligence": "2",
          "speed": "3",
          "id": 14
        }
      ],
      [
        {
          "name": "SuperGirl",
          "strength": "4",
          "intelligence": "4",
          "speed": "2",
          "id": 16
        }
      ]
    ],
    [
      [
        {
          "name": "SuperGirl",
          "strength": "4",
          "intelligence": "4",
          "speed": "2",
          "id": 16
        }
      ],
      [
        {
          "name": "Superman",
          "strength": "3",
          "intelligence": "3",
          "speed": "3",
          "id": 15
        }
      ]
    ],
    [
      [
        {
          "name": "SuperGirl",
          "strength": "4",
          "intelligence": "4",
          "speed": "2",
          "id": 16
        }
      ],
      [
        {
          "name": "Superman",
          "strength": "3",
          "intelligence": "3",
          "speed": "3",
          "id": 15
        }
      ],
      [
        {
          "name": "Barbie",
          "strength": "2",
          "intelligence": "2",
          "speed": "3",
          "id": 14
        }
      ]
    ],
    [
      [
        {
          "name": "SuperGirl",
          "strength": "4",
          "intelligence": "4",
          "speed": "2",
          "id": 16
        }
      ],
      [
        {
          "name": "Superman",
          "strength": "3",
          "intelligence": "3",
          "speed": "3",
          "id": 15
        }
      ],
      [
        {
          "name": "Barbie",
          "strength": "2",
          "intelligence": "2",
          "speed": "3",
          "id": 14
        }
      ],
      [
        {
          "name": "SuperGirl",
          "strength": "4",
          "intelligence": "4",
          "speed": "2",
          "id": 16
        }
      ]
    ],
    [
      [
        {
          "name": "Lux",
          "strength": "1",
          "intelligence": "1",
          "speed": "1",
          "id": 17
        }
      ],
      [
        {
          "name": "Lux",
          "strength": "1",
          "intelligence": "1",
          "speed": "1",
          "id": 17
        }
      ]
    ],
    [
      [
        {
          "name": "Lux",
          "strength": "1",
          "intelligence": "1",
          "speed": "1",
          "id": 17
        }
      ]
    ],
    [
      [
        {
          "name": "Lux",
          "strength": "1",
          "intelligence": "1",
          "speed": "1",
          "id": 17
        }
      ],
      [
        {
          "name": "SuperGirl",
          "strength": "4",
          "intelligence": "4",
          "speed": "2",
          "id": 16
        }
      ]
    ],
    [
      [
        {
          "name": "Lux",
          "strength": "1",
          "intelligence": "1",
          "speed": "1",
          "id": 17
        }
      ]
    ],
    [
      [
        {
          "name": "Lux",
          "strength": "1",
          "intelligence": "1",
          "speed": "1",
          "id": 17
        }
      ],
      [
        {
          "name": "SuperGirl",
          "strength": "4",
          "intelligence": "4",
          "speed": "2",
          "id": 16
        }
      ]
    ],
    [
      [
        {
          "name": "Lux",
          "strength": "1",
          "intelligence": "1",
          "speed": "1",
          "id": 17
        }
      ],
      [
        {
          "name": "SuperGirl",
          "strength": "4",
          "intelligence": "4",
          "speed": "2",
          "id": 16
        }
      ],
      [
        {
          "name": "Lux",
          "strength": "1",
          "intelligence": "1",
          "speed": "1",
          "id": 17
        }
      ]
    ],
    [
      [
        {
          "name": "Lux",
          "strength": "1",
          "intelligence": "1",
          "speed": "1",
          "id": 17
        }
      ],
      [
        {
          "name": "SuperGirl",
          "strength": "4",
          "intelligence": "4",
          "speed": "2",
          "id": 16
        }
      ],
      [
        {
          "name": "Lux",
          "strength": "1",
          "intelligence": "1",
          "speed": "1",
          "id": 17
        }
      ],
      [
        {
          "name": "SuperGirl",
          "strength": "4",
          "intelligence": "4",
          "speed": "2",
          "id": 16
        }
      ],
      [
        {
          "name": "Superman",
          "strength": "3",
          "intelligence": "3",
          "speed": "3",
          "id": 15
        }
      ],
      [
        {
          "name": "Lux",
          "strength": "1",
          "intelligence": "1",
          "speed": "1",
          "id": 17
        }
      ],
      [
        {
          "name": "Barbie",
          "strength": "2",
          "intelligence": "2",
          "speed": "3",
          "id": 14
        }
      ]
    ],
    [
      [
        {
          "name": "Lux",
          "strength": "1",
          "intelligence": "1",
          "speed": "1",
          "id": 17
        }
      ],
      [
        {
          "name": "Superman",
          "strength": "3",
          "intelligence": "3",
          "speed": "3",
          "id": 15
        }
      ]
    ],
    [
      [
        {
          "name": "Lux",
          "strength": "1",
          "intelligence": "1",
          "speed": "1",
          "id": 17
        }
      ],
      [
        {
          "name": "Superman",
          "strength": "3",
          "intelligence": "3",
          "speed": "3",
          "id": 15
        }
      ],
      [
        {
          "name": "Lux",
          "strength": "1",
          "intelligence": "1",
          "speed": "1",
          "id": 17
        }
      ]
    ],
    [
      [
        {
          "name": "Lux",
          "strength": "1",
          "intelligence": "1",
          "speed": "1",
          "id": 17
        }
      ]
    ],
    [
      [
        {
          "name": "Lux",
          "strength": "1",
          "intelligence": "1",
          "speed": "1",
          "id": 17
        }
      ]
    ],
    [
      [
        {
          "name": "Lux",
          "strength": "1",
          "intelligence": "1",
          "speed": "1",
          "id": 17
        }
      ],
      [
        {
          "name": "Lux",
          "strength": "1",
          "intelligence": "1",
          "speed": "1",
          "id": 17
        }
      ],
      [
        {
          "name": "SuperGirl",
          "strength": "4",
          "intelligence": "4",
          "speed": "2",
          "id": 16
        }
      ],
      [
        {
          "name": "Lux",
          "strength": "1",
          "intelligence": "1",
          "speed": "1",
          "id": 17
        }
      ]
    ],
    [
      [
        {
          "name": "Lux",
          "strength": "1",
          "intelligence": "1",
          "speed": "1",
          "id": 17
        }
      ]
    ]
  ]
}